happy_rag_friends/__init__.py
happy_rag_friends/cli.py
happy_rag_friends/first_time_setup.py
happy_rag_friends/routes.py
happy_rag_friends/static/styles.css
happy_rag_friends/templates/base.html
happy_rag_friends/templates/components/navbar.html
happy_rag_friends/templates/pages/about.html
happy_rag_friends/templates/pages/advisor-settings.html
happy_rag_friends/templates/pages/ask-a-question.html
happy_rag_friends/templates/pages/general-settings.html
happy_rag_friends/templates/pages/home.html
happy_rag_friends-0.1.0.dist-info/LICENSE
happy_rag_friends-0.1.0.dist-info/METADATA
happy_rag_friends-0.1.0.dist-info/WHEEL
happy_rag_friends-0.1.0.dist-info/entry_points.txt
happy_rag_friends-0.1.0.dist-info/RECORD
